{"nodes": [{"id": "apps_web_src_main_tsx", "label": "main.tsx", "file_type": "code", "source_file": "apps\\web\\src\\main.tsx", "source_location": "L1"}], "edges": [{"source": "apps_web_src_main_tsx", "target": "react", "relation": "imports_from", "confidence": "EXTRACTED", "source_file": "apps\\web\\src\\main.tsx", "source_location": "L1", "weight": 1.0}, {"source": "apps_web_src_main_tsx", "target": "client", "relation": "imports_from", "confidence": "EXTRACTED", "source_file": "apps\\web\\src\\main.tsx", "source_location": "L2", "weight": 1.0}, {"source": "apps_web_src_main_tsx", "target": "react_router_dom", "relation": "imports_from", "confidence": "EXTRACTED", "source_file": "apps\\web\\src\\main.tsx", "source_location": "L3", "weight": 1.0}, {"source": "apps_web_src_main_tsx", "target": "authcontext", "relation": "imports_from", "confidence": "EXTRACTED", "source_file": "apps\\web\\src\\main.tsx", "source_location": "L5", "weight": 1.0}, {"source": "apps_web_src_main_tsx", "target": "requireauth", "relation": "imports_from", "confidence": "EXTRACTED", "source_file": "apps\\web\\src\\main.tsx", "source_location": "L6", "weight": 1.0}, {"source": "apps_web_src_main_tsx", "target": "applayout", "relation": "imports_from", "confidence": "EXTRACTED", "source_file": "apps\\web\\src\\main.tsx", "source_location": "L7", "weight": 1.0}, {"source": "apps_web_src_main_tsx", "target": "chatpage", "relation": "imports_from", "confidence": "EXTRACTED", "source_file": "apps\\web\\src\\main.tsx", "source_location": "L8", "weight": 1.0}, {"source": "apps_web_src_main_tsx", "target": "docsragpage", "relation": "imports_from", "confidence": "EXTRACTED", "source_file": "apps\\web\\src\\main.tsx", "source_location": "L9", "weight": 1.0}, {"source": "apps_web_src_main_tsx", "target": "marketplacepage", "relation": "imports_from", "confidence": "EXTRACTED", "source_file": "apps\\web\\src\\main.tsx", "source_location": "L10", "weight": 1.0}, {"source": "apps_web_src_main_tsx", "target": "nodebuilderpage", "relation": "imports_from", "confidence": "EXTRACTED", "source_file": "apps\\web\\src\\main.tsx", "source_location": "L11", "weight": 1.0}, {"source": "apps_web_src_main_tsx", "target": "skillbuilderpage", "relation": "imports_from", "confidence": "EXTRACTED", "source_file": "apps\\web\\src\\main.tsx", "source_location": "L12", "weight": 1.0}, {"source": "apps_web_src_main_tsx", "target": "settingspage", "relation": "imports_from", "confidence": "EXTRACTED", "source_file": "apps\\web\\src\\main.tsx", "source_location": "L13", "weight": 1.0}, {"source": "apps_web_src_main_tsx", "target": "loginpage", "relation": "imports_from", "confidence": "EXTRACTED", "source_file": "apps\\web\\src\\main.tsx", "source_location": "L14", "weight": 1.0}, {"source": "apps_web_src_main_tsx", "target": "registerpage", "relation": "imports_from", "confidence": "EXTRACTED", "source_file": "apps\\web\\src\\main.tsx", "source_location": "L15", "weight": 1.0}, {"source": "apps_web_src_main_tsx", "target": "apps_web_src_index_css", "relation": "imports_from", "confidence": "EXTRACTED", "source_file": "apps\\web\\src\\main.tsx", "source_location": "L16", "weight": 1.0}], "raw_calls": []}